uopenai-0.2.3.dist-info/METADATA
uopenai-0.2.3.dist-info/WHEEL
uopenai-0.2.3.dist-info/licenses/LICENSE
uopenai/__init__.py
uopenai/core.py
uopenai/py.typed
uopenai-0.2.3.dist-info/RECORD
