Metadata-Version: 2.1
Name: uopenai
Version: 0.2.3
Summary: Minimalistic library to call OpenAI API, with httpx and type-hinting
Author-Email: Grigory Bakunov <bobuk@rubedo.cloud>
License: Unlicense
Requires-Python: >=3.9
Requires-Dist: httpx>=0.19.0
Requires-Dist: pydantic>=2.0.0
